{"Albacete":{"cartodb_id":4152,"x_coordinate":-112.98701298701299,"y_coordinate":125.3740980930199,"radius":59.17338458082711,"color":["#D94B5F"],"children_json_url":null,"censo_total":120201,"porcentaje_participacion":65.28897430137852,"partido_1":["PSOE",47.0],"partido_2":["PP",42.0],"partido_3":["IU",6.0],"resto_partidos_percent":4,"info":"","parent":["Castilla-La_Mancha","Albacete"],"parent_url":["json/generated_data/autonomias/paro_normalizado_2003.json","json/generated_data/provincias/Castilla-La_Mancha_paro_normalizado_2003.json"],"parent_results":{"partido_1":["PSOE",44],"partido_2":["PP",17],"partido_3":["IU",5],"otros":["Otros",33]},"evolution":"2.4925230769999995,1.4723076920000002,1.333138462,1.1718461539999998,1.071507692,1.0692923079999996,1.1223076919999997,1.1808923080000002,0.9743999999999997,1.1379384620000002,0.9053230770000003,0.5955090740000002,0.4380073799999993,0.7811193109999994"},"Hellín":{"cartodb_id":4203,"x_coordinate":-131.16883116883116,"y_coordinate":153.3074898997568,"radius":62.352124409886144,"color":["#D94B5F"],"children_json_url":null,"censo_total":21606,"porcentaje_participacion":70.58687401647691,"partido_1":["PSOE",47.0],"partido_2":["PP",35.0],"partido_3":["IU",6.0],"resto_partidos_percent":10,"info":"","parent":["Castilla-La_Mancha","Albacete"],"parent_url":["json/generated_data/autonomias/paro_normalizado_2003.json","json/generated_data/provincias/Castilla-La_Mancha_paro_normalizado_2003.json"],"parent_results":{"partido_1":["PSOE",44],"partido_2":["PP",17],"partido_3":["IU",5],"otros":["Otros",33]},"evolution":"3.892523077,3.4723076920000002,3.2331384619999994,3.171846154,2.571507692,2.469292308,2.322307692,2.480892308,2.4743999999999997,3.0379384619999996,3.005323077,2.9955090740000005,3.538007379999999,4.4811193110000005"},"Almansa":{"cartodb_id":4186,"x_coordinate":-123.37662337662337,"y_coordinate":129.67154298636402,"radius":63.824067778881854,"color":["#D94B5F"],"children_json_url":null,"censo_total":19121,"porcentaje_participacion":73.0401129648031,"partido_1":["PSOE",44.0],"partido_2":["PP",35.0],"partido_3":["AEIA",8.0],"resto_partidos_percent":11,"info":"","parent":["Castilla-La_Mancha","Albacete"],"parent_url":["json/generated_data/autonomias/paro_normalizado_2003.json","json/generated_data/provincias/Castilla-La_Mancha_paro_normalizado_2003.json"],"parent_results":{"partido_1":["PSOE",44],"partido_2":["PP",17],"partido_3":["IU",5],"otros":["Otros",33]},"evolution":"1.8925230769999999,0.772307692,0.9331384619999996,1.0718461540000002,0.7715076919999997,0.06929230800000008,-0.17769230800000013,1.3808923079999995,1.6743999999999999,2.237938462,2.6053230769999995,2.595509074,2.03800738,4.581119311"},"Villarrobledo":{"cartodb_id":4216,"x_coordinate":-188.31168831168833,"y_coordinate":-99.58942873295504,"radius":65.72121896162528,"color":["#D94B5F"],"children_json_url":null,"censo_total":17720,"porcentaje_participacion":76.20203160270881,"partido_1":["PSOE",56.0],"partido_2":["PP",22.0],"partido_3":["A.I.V.",19.0],"resto_partidos_percent":2,"info":"","parent":["Castilla-La_Mancha","Albacete"],"parent_url":["json/generated_data/autonomias/paro_normalizado_2003.json","json/generated_data/provincias/Castilla-La_Mancha_paro_normalizado_2003.json"],"parent_results":{"partido_1":["PSOE",44],"partido_2":["PP",17],"partido_3":["IU",5],"otros":["Otros",33]},"evolution":"0.49252307699999953,0.1723076920000004,-0.5668615380000004,-0.3281538460000002,-0.3284923080000004,-0.1307076920000001,-0.2776923080000002,-0.019107691999999954,-0.22560000000000002,-0.2620615380000002,0.005323076999999898,0.49550907400000055,0.6380073799999995,2.381119310999999"},"La_Roda":{"cartodb_id":4209,"x_coordinate":115.58441558441558,"y_coordinate":101.7381511796271,"radius":69.41778056876291,"color":["#64B7DE"],"children_json_url":null,"censo_total":11147,"porcentaje_participacion":82.36296761460483,"partido_1":["PP",52.0],"partido_2":["PSOE",46.0],"partido_3":["A.E.A",0.0],"resto_partidos_percent":1,"info":"","parent":["Castilla-La_Mancha","Albacete"],"parent_url":["json/generated_data/autonomias/paro_normalizado_2003.json","json/generated_data/provincias/Castilla-La_Mancha_paro_normalizado_2003.json"],"parent_results":{"partido_1":["PSOE",44],"partido_2":["PP",17],"partido_3":["IU",5],"otros":["Otros",33]},"evolution":"-0.007476923000000468,-1.1276923079999994,-0.7668615380000001,-0.3281538460000002,-0.2284923080000003,0.06929230800000008,0.12230769199999969,0.08089230799999969,0.0743999999999998,0.6379384620000002,0.6053230769999995,1.0955090740000002,0.8380073799999996,0.9811193109999996"},"Fuente-Álamo":{"cartodb_id":4190,"x_coordinate":167.53246753246754,"y_coordinate":-56.614979799513605,"radius":65.40748334187596,"color":["#64B7DE"],"children_json_url":null,"censo_total":7804,"porcentaje_participacion":75.6791389031266,"partido_1":["PP",57.0],"partido_2":["PSOE",31.0],"partido_3":["IU",9.0],"resto_partidos_percent":2,"info":"","parent":["Castilla-La_Mancha","Albacete"],"parent_url":["json/generated_data/autonomias/paro_normalizado_2003.json","json/generated_data/provincias/Castilla-La_Mancha_paro_normalizado_2003.json"],"parent_results":{"partido_1":["PSOE",44],"partido_2":["PP",17],"partido_3":["IU",5],"otros":["Otros",33]},"evolution":"-2.507476923,-2.6276923079999994,-2.4668615380000003,-1.8281538460000002,-1.8284923080000002,-1.830707692,-2.077692308,-2.0191076920000004,-2.5256,-2.762061538,-2.594676923,-2.204490926,-1.6619926200000004,-1.118880689"},"Caudete":{"cartodb_id":4189,"x_coordinate":-149.35064935064935,"y_coordinate":114.63048585965953,"radius":68.29370045890697,"color":["#D94B5F"],"children_json_url":null,"censo_total":7191,"porcentaje_participacion":80.48950076484495,"partido_1":["PSOE",57.0],"partido_2":["PP",38.0],"partido_3":["IU",3.0],"resto_partidos_percent":1,"info":"","parent":["Castilla-La_Mancha","Albacete"],"parent_url":["json/generated_data/autonomias/paro_normalizado_2003.json","json/generated_data/provincias/Castilla-La_Mancha_paro_normalizado_2003.json"],"parent_results":{"partido_1":["PSOE",44],"partido_2":["PP",17],"partido_3":["IU",5],"otros":["Otros",33]},"evolution":"0.29252307700000024,1.272307692,0.4331384619999996,-0.5281538460000004,-0.6284923080000002,-0.2307076920000002,0.8223076919999999,0.6808923079999998,0.6743999999999999,1.1379384620000002,1.005323077,1.5955090740000002,2.03800738,4.781119310999999"},"Tobarra":{"cartodb_id":4207,"x_coordinate":-115.58441558441558,"y_coordinate":125.3740980930199,"radius":67.78390655418559,"color":["#D94B5F"],"children_json_url":null,"censo_total":6164,"porcentaje_participacion":79.63984425697599,"partido_1":["PSOE",46.0],"partido_2":["PP",40.0],"partido_3":["IU",10.0],"resto_partidos_percent":2,"info":"","parent":["Castilla-La_Mancha","Albacete"],"parent_url":["json/generated_data/autonomias/paro_normalizado_2003.json","json/generated_data/provincias/Castilla-La_Mancha_paro_normalizado_2003.json"],"parent_results":{"partido_1":["PSOE",44],"partido_2":["PP",17],"partido_3":["IU",5],"otros":["Otros",33]},"evolution":"1.6925230769999997,2.272307692,2.033138462,0.871846154,1.2715076920000001,1.5692923079999996,1.022307692,1.1808923080000002,1.4743999999999997,2.0379384619999996,1.705323077,1.7955090740000004,1.6380073799999995,1.7811193109999994"},"Tarazona_de_la_Mancha":{"cartodb_id":4214,"x_coordinate":-128.57142857142858,"y_coordinate":121.07665319967575,"radius":66.49819494584838,"color":["#D94B5F"],"children_json_url":null,"censo_total":4986,"porcentaje_participacion":77.49699157641395,"partido_1":["PSOE",50.0],"partido_2":["PP",39.0],"partido_3":["IU",8.0],"resto_partidos_percent":1,"info":"","parent":["Castilla-La_Mancha","Albacete"],"parent_url":["json/generated_data/autonomias/paro_normalizado_2003.json","json/generated_data/provincias/Castilla-La_Mancha_paro_normalizado_2003.json"],"parent_results":{"partido_1":["PSOE",44],"partido_2":["PP",17],"partido_3":["IU",5],"otros":["Otros",33]},"evolution":"2.592523077,1.9723076920000002,1.0331384620000001,1.6718461539999998,2.1715076919999996,2.469292308,2.022307692,0.980892308,1.3744,2.8379384620000003,3.9053230770000003,3.095509074,2.6380073799999995,3.081119311"},"Madrigueras":{"cartodb_id":4175,"x_coordinate":-102.59740259740259,"y_coordinate":136.11771032638023,"radius":70.71582346609257,"color":["#54A551"],"children_json_url":null,"censo_total":3716,"porcentaje_participacion":84.52637244348762,"partido_1":["IU",39.0],"partido_2":["PSOE",38.0],"partido_3":["PP",20.0],"resto_partidos_percent":2,"info":"","parent":["Castilla-La_Mancha","Albacete"],"parent_url":["json/generated_data/autonomias/paro_normalizado_2003.json","json/generated_data/provincias/Castilla-La_Mancha_paro_normalizado_2003.json"],"parent_results":{"partido_1":["PSOE",44],"partido_2":["PP",17],"partido_3":["IU",5],"otros":["Otros",33]},"evolution":"2.1925230769999997,1.272307692,0.1331384619999998,0.371846154,0.571507692,1.3692923080000003,1.522307692,1.6808923080000002,2.1744,2.937938462,3.8053230769999997,2.695509074,2.9380073799999993,3.381119310999999"},"Yeste":{"cartodb_id":4201,"x_coordinate":128.57142857142858,"y_coordinate":183.3896041531658,"radius":61.32987910189983,"color":["#64B7DE"],"children_json_url":null,"censo_total":3474,"porcentaje_participacion":68.88313183649971,"partido_1":["PP",52.0],"partido_2":["PSOE",41.0],"partido_3":["IU",5.0],"resto_partidos_percent":0,"info":"","parent":["Castilla-La_Mancha","Albacete"],"parent_url":["json/generated_data/autonomias/paro_normalizado_2003.json","json/generated_data/provincias/Castilla-La_Mancha_paro_normalizado_2003.json"],"parent_results":{"partido_1":["PSOE",44],"partido_2":["PP",17],"partido_3":["IU",5],"otros":["Otros",33]},"evolution":"3.6925230770000006,3.0723076920000008,3.7331384619999994,4.371846154,3.771507692,4.169292308,3.9223076919999995,3.8808923079999995,4.074400000000001,5.437938462,5.505323077,6.195509074,5.038007379999999,3.7811193109999994"},"Casas-Ibáñez":{"cartodb_id":3879,"x_coordinate":-128.57142857142858,"y_coordinate":121.07665319967575,"radius":67.28077945084145,"color":["#D94B5F"],"children_json_url":null,"censo_total":3387,"porcentaje_participacion":78.80129908473576,"partido_1":["PSOE",49.0],"partido_2":["PP",38.0],"partido_3":["IU",8.0],"resto_partidos_percent":3,"info":"","parent":["Castilla-La_Mancha","Albacete"],"parent_url":["json/generated_data/autonomias/paro_normalizado_2003.json","json/generated_data/provincias/Castilla-La_Mancha_paro_normalizado_2003.json"],"parent_results":{"partido_1":["PSOE",44],"partido_2":["PP",17],"partido_3":["IU",5],"otros":["Otros",33]},"evolution":"2.092523077,0.27230769200000005,0.23313846199999944,0.1718461539999998,0.1715076919999996,0.469292308,0.6223076919999997,0.980892308,0.7743999999999995,1.1379384620000002,1.6053230769999995,0.49550907400000055,0.13800737999999946,0.881119311"},"Munera":{"cartodb_id":4212,"x_coordinate":-227.27272727272725,"y_coordinate":164.05110213311718,"radius":70.18614586512054,"color":["#D8282A"],"children_json_url":null,"censo_total":3277,"porcentaje_participacion":83.64357644186757,"partido_1":["PSOE",67.0],"partido_2":["PP",18.0],"partido_3":["IU",12.0],"resto_partidos_percent":1,"info":"","parent":["Castilla-La_Mancha","Albacete"],"parent_url":["json/generated_data/autonomias/paro_normalizado_2003.json","json/generated_data/provincias/Castilla-La_Mancha_paro_normalizado_2003.json"],"parent_results":{"partido_1":["PSOE",44],"partido_2":["PP",17],"partido_3":["IU",5],"otros":["Otros",33]},"evolution":"3.2925230770000002,3.972307692000001,2.033138462,1.5718461540000002,1.7715076920000001,1.969292308,2.7223076920000002,2.980892308,3.1744,3.5379384619999996,3.005323077,4.195509074,3.6380073800000003,3.181119311"},"Elche_de_la_Sierra":{"cartodb_id":4194,"x_coordinate":-136.36363636363637,"y_coordinate":174.79471436647754,"radius":67.83216783216784,"color":["#D94B5F"],"children_json_url":null,"censo_total":3146,"porcentaje_participacion":79.72027972027972,"partido_1":["PSOE",56.0],"partido_2":["PP",42.0],"partido_3":["A.E.A",0.0],"resto_partidos_percent":1,"info":"","parent":["Castilla-La_Mancha","Albacete"],"parent_url":["json/generated_data/autonomias/paro_normalizado_2003.json","json/generated_data/provincias/Castilla-La_Mancha_paro_normalizado_2003.json"],"parent_results":{"partido_1":["PSOE",44],"partido_2":["PP",17],"partido_3":["IU",5],"otros":["Otros",33]},"evolution":"3.892523077,3.0723076920000008,2.533138462,2.671846154,2.271507692,2.669292308,3.4223076919999995,3.480892308,2.9743999999999997,5.437938462,4.905323077,5.695509074,5.23800738,6.281119310999999"},"Villamalea":{"cartodb_id":4183,"x_coordinate":-159.74025974025975,"y_coordinate":106.03559607297125,"radius":69.25249741646573,"color":["#D94B5F"],"children_json_url":null,"censo_total":2903,"porcentaje_participacion":82.08749569410955,"partido_1":["PSOE",49.0],"partido_2":["IU",26.0],"partido_3":["PP",22.0],"resto_partidos_percent":2,"info":"","parent":["Castilla-La_Mancha","Albacete"],"parent_url":["json/generated_data/autonomias/paro_normalizado_2003.json","json/generated_data/provincias/Castilla-La_Mancha_paro_normalizado_2003.json"],"parent_results":{"partido_1":["PSOE",44],"partido_2":["PP",17],"partido_3":["IU",5],"otros":["Otros",33]},"evolution":"2.9925230769999995,2.272307692,1.4331384619999996,0.5718461539999997,0.8715076919999998,0.6692923080000002,0.42230769199999996,0.28089230799999987,0.2744,0.437938462,0.9053230770000003,0.9955090740000005,0.9380073799999993,0.5811193110000001"},"El_Bonillo":{"cartodb_id":4208,"x_coordinate":-112.98701298701299,"y_coordinate":149.01004500641267,"radius":73.3693972179289,"color":["#D94B5F"],"children_json_url":null,"censo_total":2588,"porcentaje_participacion":88.94899536321483,"partido_1":["PSOE",49.0],"partido_2":["PP",44.0],"partido_3":["IU",5.0],"resto_partidos_percent":1,"info":"","parent":["Castilla-La_Mancha","Albacete"],"parent_url":["json/generated_data/autonomias/paro_normalizado_2003.json","json/generated_data/provincias/Castilla-La_Mancha_paro_normalizado_2003.json"],"parent_results":{"partido_1":["PSOE",44],"partido_2":["PP",17],"partido_3":["IU",5],"otros":["Otros",33]},"evolution":"-0.20747692299999976,-0.22769230799999995,0.4331384619999996,0.47184615399999963,1.571507692,1.3692923080000003,2.7223076920000002,2.280892308,2.6744,3.137938462,4.1053230769999995,4.195509074,2.4380073799999993,1.6811193109999998"},"Ossa_de_Montiel":{"cartodb_id":4213,"x_coordinate":-183.11688311688312,"y_coordinate":226.3640530866072,"radius":69.16181084715375,"color":["#D94B5F"],"children_json_url":null,"censo_total":2231,"porcentaje_participacion":81.9363514119229,"partido_1":["PSOE",54.0],"partido_2":["IU",22.0],"partido_3":["PP",21.0],"resto_partidos_percent":2,"info":"","parent":["Castilla-La_Mancha","Albacete"],"parent_url":["json/generated_data/autonomias/paro_normalizado_2003.json","json/generated_data/provincias/Castilla-La_Mancha_paro_normalizado_2003.json"],"parent_results":{"partido_1":["PSOE",44],"partido_2":["PP",17],"partido_3":["IU",5],"otros":["Otros",33]},"evolution":"2.2925230770000002,2.3723076920000006,3.133138462,3.071846154,4.471507691999999,4.069292308,4.322307692,5.880892308,5.974400000000001,7.437938462,6.405323077,6.795509074,6.038007379999999,6.881119310999999"},"Pozo_Cañada":{"cartodb_id":4166,"x_coordinate":-157.14285714285714,"y_coordinate":166.1998245797892,"radius":68.28518173345759,"color":["#D94B5F"],"children_json_url":null,"censo_total":2146,"porcentaje_participacion":80.47530288909599,"partido_1":["PSOE",50.0],"partido_2":["AIDPC",28.0],"partido_3":["PP",20.0],"resto_partidos_percent":0,"info":"","parent":["Castilla-La_Mancha","Albacete"],"parent_url":["json/generated_data/autonomias/paro_normalizado_2003.json","json/generated_data/provincias/Castilla-La_Mancha_paro_normalizado_2003.json"],"parent_results":{"partido_1":["PSOE",44],"partido_2":["PP",17],"partido_3":["IU",5],"otros":["Otros",33]},"evolution":"-1.2074769230000002,1.4723076920000002,-3.866861538,1.371846154,1.1715076919999996,0.8692923079999999,1.8223076919999999,3.0808923079999997,2.7743999999999995,2.237938462,1.4053230770000003,1.1955090739999998,1.8380073799999996,1.381119310999999"},"Ontur":{"cartodb_id":4205,"x_coordinate":0,"y_coordinate":112.48176341298745,"radius":71.17037037037036,"color":["#AAAAAA"],"children_json_url":null,"censo_total":2025,"porcentaje_participacion":85.28395061728395,"partido_1":["AOI",44.0],"partido_2":["PSOE",41.0],"partido_3":["PP",10.0],"resto_partidos_percent":3,"info":"","parent":["Castilla-La_Mancha","Albacete"],"parent_url":["json/generated_data/autonomias/paro_normalizado_2003.json","json/generated_data/provincias/Castilla-La_Mancha_paro_normalizado_2003.json"],"parent_results":{"partido_1":["PSOE",44],"partido_2":["PP",17],"partido_3":["IU",5],"otros":["Otros",33]},"evolution":"1.3925230769999999,1.272307692,1.333138462,0.5718461539999997,0.6715076919999996,0.3692923079999999,0.8223076919999999,0.5808923079999997,1.4743999999999997,2.237938462,1.1053230769999995,0.6955090739999998,1.73800738,1.6811193109999998"},"Alpera":{"cartodb_id":4187,"x_coordinate":115.58441558441558,"y_coordinate":155.45621234642888,"radius":72.22339304531086,"color":["#64B7DE"],"children_json_url":null,"censo_total":1898,"porcentaje_participacion":87.03898840885142,"partido_1":["PP",51.0],"partido_2":["PSOE",45.0],"partido_3":["A.E.A",0.0],"resto_partidos_percent":3,"info":"","parent":["Castilla-La_Mancha","Albacete"],"parent_url":["json/generated_data/autonomias/paro_normalizado_2003.json","json/generated_data/provincias/Castilla-La_Mancha_paro_normalizado_2003.json"],"parent_results":{"partido_1":["PSOE",44],"partido_2":["PP",17],"partido_3":["IU",5],"otros":["Otros",33]},"evolution":"1.1925230769999997,1.3723076920000006,1.333138462,0.6718461539999998,0.6715076919999996,1.1692923080000002,0.9223076919999995,2.5808923079999997,2.3744,2.937938462,2.205323077,2.895509074,3.3380073799999996,4.381119310999999"},"Balazote":{"cartodb_id":4218,"x_coordinate":-157.14285714285714,"y_coordinate":222.0666081932631,"radius":74.48467966573816,"color":["#D94B5F"],"children_json_url":null,"censo_total":1795,"porcentaje_participacion":90.80779944289694,"partido_1":["PSOE",55.0],"partido_2":["PP",33.0],"partido_3":["IU",10.0],"resto_partidos_percent":0,"info":"","parent":["Castilla-La_Mancha","Albacete"],"parent_url":["json/generated_data/autonomias/paro_normalizado_2003.json","json/generated_data/provincias/Castilla-La_Mancha_paro_normalizado_2003.json"],"parent_results":{"partido_1":["PSOE",44],"partido_2":["PP",17],"partido_3":["IU",5],"otros":["Otros",33]},"evolution":"8.492523077,7.472307692000001,7.4331384620000005,5.2718461539999995,6.071507691999999,6.269292308000001,5.122307692000001,5.680892308000001,4.074400000000001,3.437938462,3.9053230770000003,3.4955090740000005,3.73800738,3.4811193110000005"},"Montealegre_del_Castillo":{"cartodb_id":4191,"x_coordinate":136.36363636363637,"y_coordinate":-84.54837160625054,"radius":67.30703259005145,"color":["#64B7DE"],"children_json_url":null,"censo_total":1749,"porcentaje_participacion":78.84505431675242,"partido_1":["PP",55.0],"partido_2":["PSOE",41.0],"partido_3":["A.E.A",0.0],"resto_partidos_percent":3,"info":"","parent":["Castilla-La_Mancha","Albacete"],"parent_url":["json/generated_data/autonomias/paro_normalizado_2003.json","json/generated_data/provincias/Castilla-La_Mancha_paro_normalizado_2003.json"],"parent_results":{"partido_1":["PSOE",44],"partido_2":["PP",17],"partido_3":["IU",5],"otros":["Otros",33]},"evolution":"0.1925230769999997,-0.027692307999999777,-0.7668615380000001,-0.9281538460000003,-0.3284923080000004,-0.7307076920000002,-0.977692308,-0.7191076920000001,-0.6255999999999999,-0.2620615380000002,0.3053230769999997,0.5955090740000002,0.8380073799999996,0.38111931099999996"},"Socovos":{"cartodb_id":4200,"x_coordinate":-157.14285714285714,"y_coordinate":234.9589428732955,"radius":64.87135506003432,"color":["#D94B5F"],"children_json_url":null,"censo_total":1749,"porcentaje_participacion":74.78559176672384,"partido_1":["PSOE",43.0],"partido_2":["PP",21.0],"partido_3":["AESOC",20.0],"resto_partidos_percent":15,"info":"","parent":["Castilla-La_Mancha","Albacete"],"parent_url":["json/generated_data/autonomias/paro_normalizado_2003.json","json/generated_data/provincias/Castilla-La_Mancha_paro_normalizado_2003.json"],"parent_results":{"partido_1":["PSOE",44],"partido_2":["PP",17],"partido_3":["IU",5],"otros":["Otros",33]},"evolution":"6.892523077,6.772307692,6.833138461999999,6.871846153999999,6.871507692,6.269292308000001,7.222307692,6.280892308,8.0744,8.837938462,8.005323077,8.295509074,6.83800738,7.281119310999999"},"La_Gineta":{"cartodb_id":4158,"x_coordinate":-146.75324675324674,"y_coordinate":131.8202654330361,"radius":72.75681950087058,"color":["#D94B5F"],"children_json_url":null,"censo_total":1723,"porcentaje_participacion":87.92803250145096,"partido_1":["PSOE",43.0],"partido_2":["P.I.A.",25.0],"partido_3":["PP",17.0],"resto_partidos_percent":13,"info":"","parent":["Castilla-La_Mancha","Albacete"],"parent_url":["json/generated_data/autonomias/paro_normalizado_2003.json","json/generated_data/provincias/Castilla-La_Mancha_paro_normalizado_2003.json"],"parent_results":{"partido_1":["PSOE",44],"partido_2":["PP",17],"partido_3":["IU",5],"otros":["Otros",33]},"evolution":"-0.007476923000000468,0.4723076920000002,-0.666861538,-0.2281538460000001,0.3715076919999998,1.3692923080000003,1.9223076919999995,1.480892308,0.5743999999999998,1.6379384620000002,1.8053230769999997,1.6955090739999998,1.1380073799999995,2.2811193109999994"},"Valdeganga":{"cartodb_id":4180,"x_coordinate":-131.16883116883116,"y_coordinate":151.15876745308475,"radius":70.58682634730539,"color":["#D94B5F"],"children_json_url":null,"censo_total":1670,"porcentaje_participacion":84.31137724550898,"partido_1":["PSOE",55.0],"partido_2":["PP",43.0],"partido_3":["A.E.A",0.0],"resto_partidos_percent":1,"info":"","parent":["Castilla-La_Mancha","Albacete"],"parent_url":["json/generated_data/autonomias/paro_normalizado_2003.json","json/generated_data/provincias/Castilla-La_Mancha_paro_normalizado_2003.json"],"parent_results":{"partido_1":["PSOE",44],"partido_2":["PP",17],"partido_3":["IU",5],"otros":["Otros",33]},"evolution":"4.9925230769999995,4.672307692,3.7331384619999994,2.671846154,2.871507692,2.469292308,2.2223076920000002,2.3808923079999995,2.8744,2.0379384619999996,1.9053230770000003,2.695509074,0.73800738,1.0811193110000001"},"Pozohondo":{"cartodb_id":4206,"x_coordinate":-175.32467532467533,"y_coordinate":219.91788574659103,"radius":70.80318822808093,"color":["#D94B5F"],"children_json_url":null,"censo_total":1631,"porcentaje_participacion":84.67198038013488,"partido_1":["PSOE",63.0],"partido_2":["PP",34.0],"partido_3":["A.E.A",0.0],"resto_partidos_percent":1,"info":"","parent":["Castilla-La_Mancha","Albacete"],"parent_url":["json/generated_data/autonomias/paro_normalizado_2003.json","json/generated_data/provincias/Castilla-La_Mancha_paro_normalizado_2003.json"],"parent_results":{"partido_1":["PSOE",44],"partido_2":["PP",17],"partido_3":["IU",5],"otros":["Otros",33]},"evolution":"3.892523077,4.972307692000001,4.533138462,4.171846154,4.271507692,4.369292308,4.722307692,5.580892308000001,4.2744,5.837938462,4.305323077000001,4.595509074000001,3.9380073799999993,4.381119310999999"},"Barrax":{"cartodb_id":4154,"x_coordinate":120.77922077922078,"y_coordinate":151.15876745308475,"radius":73.80670611439842,"color":["#64B7DE"],"children_json_url":null,"censo_total":1521,"porcentaje_participacion":89.67784352399737,"partido_1":["PP",48.0],"partido_2":["PSOE",40.0],"partido_3":["IU",10.0],"resto_partidos_percent":0,"info":"","parent":["Castilla-La_Mancha","Albacete"],"parent_url":["json/generated_data/autonomias/paro_normalizado_2003.json","json/generated_data/provincias/Castilla-La_Mancha_paro_normalizado_2003.json"],"parent_results":{"partido_1":["PSOE",44],"partido_2":["PP",17],"partido_3":["IU",5],"otros":["Otros",33]},"evolution":"4.692523077000001,0.07230769200000076,0.5331384620000001,0.371846154,0.8715076919999998,0.969292308,0.6223076919999997,2.3808923079999995,2.2743999999999995,4.037938462,3.8053230769999997,4.495509074000001,4.038007379999999,4.881119310999999"},"Fuentealbilla":{"cartodb_id":4164,"x_coordinate":-105.1948051948052,"y_coordinate":174.79471436647754,"radius":69.50201884253028,"color":["#D94B5F"],"children_json_url":null,"censo_total":1486,"porcentaje_participacion":82.50336473755047,"partido_1":["PSOE",47.0],"partido_2":["PP",45.0],"partido_3":["IU",6.0],"resto_partidos_percent":1,"info":"","parent":["Castilla-La_Mancha","Albacete"],"parent_url":["json/generated_data/autonomias/paro_normalizado_2003.json","json/generated_data/provincias/Castilla-La_Mancha_paro_normalizado_2003.json"],"parent_results":{"partido_1":["PSOE",44],"partido_2":["PP",17],"partido_3":["IU",5],"otros":["Otros",33]},"evolution":"4.892523077,4.272307692,3.4331384619999996,3.9718461539999996,2.771507692,3.969292308,2.522307692,3.480892308,2.2743999999999995,2.637938462,2.705323077,2.595509074,1.9380073799999993,1.881119310999999"},"Alcaraz":{"cartodb_id":4217,"x_coordinate":-157.14285714285714,"y_coordinate":112.48176341298745,"radius":68.55983772819474,"color":["#D94B5F"],"children_json_url":null,"censo_total":1479,"porcentaje_participacion":80.93306288032454,"partido_1":["PSOE",60.0],"partido_2":["PP",38.0],"partido_3":["A.E.A",0.0],"resto_partidos_percent":0,"info":"","parent":["Castilla-La_Mancha","Albacete"],"parent_url":["json/generated_data/autonomias/paro_normalizado_2003.json","json/generated_data/provincias/Castilla-La_Mancha_paro_normalizado_2003.json"],"parent_results":{"partido_1":["PSOE",44],"partido_2":["PP",17],"partido_3":["IU",5],"otros":["Otros",33]},"evolution":"2.9925230769999995,4.872307692,3.7331384619999994,0.5718461539999997,3.571507692,3.5692923079999996,1.3223076919999999,0.5808923079999997,2.0744000000000002,2.737938462,2.8053230769999997,2.7955090740000004,3.23800738,2.2811193109999994"},"Minaya":{"cartodb_id":4211,"x_coordinate":-100.0,"y_coordinate":110.3330409663154,"radius":72.04330175913397,"color":["#D94B5F"],"children_json_url":null,"censo_total":1478,"porcentaje_participacion":86.73883626522327,"partido_1":["PSOE",49.0],"partido_2":["PP",49.0],"partido_3":["A.E.A",0.0],"resto_partidos_percent":1,"info":"","parent":["Castilla-La_Mancha","Albacete"],"parent_url":["json/generated_data/autonomias/paro_normalizado_2003.json","json/generated_data/provincias/Castilla-La_Mancha_paro_normalizado_2003.json"],"parent_results":{"partido_1":["PSOE",44],"partido_2":["PP",17],"partido_3":["IU",5],"otros":["Otros",33]},"evolution":"1.1925230769999997,0.07230769200000076,0.0331384619999997,-0.4281538460000003,-0.2284923080000003,0.5692923080000001,0.022307692000000046,0.48089230800000005,-0.5256000000000003,0.03793846199999962,0.6053230769999995,0.7955090740000004,-0.36199262000000054,0.08111931100000014"},"Lezuza":{"cartodb_id":4210,"x_coordinate":-123.37662337662337,"y_coordinate":125.3740980930199,"radius":74.46601941747574,"color":["#D94B5F"],"children_json_url":null,"censo_total":1442,"porcentaje_participacion":90.77669902912622,"partido_1":["PSOE",54.0],"partido_2":["PP",45.0],"partido_3":["A.E.A",0.0],"resto_partidos_percent":0,"info":"","parent":["Castilla-La_Mancha","Albacete"],"parent_url":["json/generated_data/autonomias/paro_normalizado_2003.json","json/generated_data/provincias/Castilla-La_Mancha_paro_normalizado_2003.json"],"parent_results":{"partido_1":["PSOE",44],"partido_2":["PP",17],"partido_3":["IU",5],"otros":["Otros",33]},"evolution":"0.6925230769999997,0.772307692,-0.666861538,1.371846154,1.4715076919999994,0.8692923079999999,1.522307692,1.1808923080000002,1.4743999999999997,0.8379384620000003,0.3053230769999997,1.4955090740000005,0.5380073799999998,-0.018880689000000395"},"Nerpio":{"cartodb_id":4199,"x_coordinate":-144.15584415584416,"y_coordinate":207.0255510665586,"radius":63.64016736401673,"color":["#D94B5F"],"children_json_url":null,"censo_total":1434,"porcentaje_participacion":72.73361227336123,"partido_1":["PSOE",57.0],"partido_2":["PP",40.0],"partido_3":["A.E.A",0.0],"resto_partidos_percent":1,"info":"","parent":["Castilla-La_Mancha","Albacete"],"parent_url":["json/generated_data/autonomias/paro_normalizado_2003.json","json/generated_data/provincias/Castilla-La_Mancha_paro_normalizado_2003.json"],"parent_results":{"partido_1":["PSOE",44],"partido_2":["PP",17],"partido_3":["IU",5],"otros":["Otros",33]},"evolution":"2.892523077,4.172307692,3.633138462,3.871846154,5.1715076920000005,4.569292308,4.522307692,4.980892308,4.574400000000001,6.537938462,4.505323077,3.695509074,3.1380073799999995,2.4811193110000005"},"Liétor":{"cartodb_id":4204,"x_coordinate":-151.94805194805195,"y_coordinate":250.0,"radius":67.90697674418604,"color":["#D94B5F"],"children_json_url":null,"censo_total":1419,"porcentaje_participacion":79.84496124031007,"partido_1":["PSOE",56.0],"partido_2":["PP",36.0],"partido_3":["IU",6.0],"resto_partidos_percent":0,"info":"","parent":["Castilla-La_Mancha","Albacete"],"parent_url":["json/generated_data/autonomias/paro_normalizado_2003.json","json/generated_data/provincias/Castilla-La_Mancha_paro_normalizado_2003.json"],"parent_results":{"partido_1":["PSOE",44],"partido_2":["PP",17],"partido_3":["IU",5],"otros":["Otros",33]},"evolution":"5.192523077000001,5.772307692,6.733138461999999,6.071846154,6.271507692,5.869292308,5.822307692,6.980892308,4.6744,8.037938462,9.405323077,9.095509074,7.23800738,9.981119311"},"Alcalá_del_Júcar":{"cartodb_id":4171,"x_coordinate":-209.0909090909091,"y_coordinate":133.96898787970815,"radius":69.71025841816757,"color":["#D8282A"],"children_json_url":null,"censo_total":1277,"porcentaje_participacion":82.85043069694596,"partido_1":["PSOE",70.0],"partido_2":["PP",28.0],"partido_3":["A.E.A",0.0],"resto_partidos_percent":1,"info":"","parent":["Castilla-La_Mancha","Albacete"],"parent_url":["json/generated_data/autonomias/paro_normalizado_2003.json","json/generated_data/provincias/Castilla-La_Mancha_paro_normalizado_2003.json"],"parent_results":{"partido_1":["PSOE",44],"partido_2":["PP",17],"partido_3":["IU",5],"otros":["Otros",33]},"evolution":"3.6925230770000006,2.6723076920000004,3.533138462,1.6718461539999998,1.6715076919999996,1.2692923079999998,0.7223076919999998,1.5808923079999997,1.5744000000000002,-0.06206153800000003,1.005323077,0.895509074,0.13800737999999946,-0.8188806890000002"},"Mahora":{"cartodb_id":4176,"x_coordinate":157.14285714285714,"y_coordinate":202.72810617321443,"radius":71.86524239934265,"color":["#64B7DE"],"children_json_url":null,"censo_total":1217,"porcentaje_participacion":86.44207066557108,"partido_1":["PP",60.0],"partido_2":["PSOE",38.0],"partido_3":["A.E.A",0.0],"resto_partidos_percent":0,"info":"","parent":["Castilla-La_Mancha","Albacete"],"parent_url":["json/generated_data/autonomias/paro_normalizado_2003.json","json/generated_data/provincias/Castilla-La_Mancha_paro_normalizado_2003.json"],"parent_results":{"partido_1":["PSOE",44],"partido_2":["PP",17],"partido_3":["IU",5],"otros":["Otros",33]},"evolution":"5.392523077,5.772307692,3.533138462,3.4718461539999996,3.071507692,3.8692923080000003,3.9223076919999995,4.780892308,4.474399999999999,3.437938462,2.9053230770000003,3.595509074,1.5380073799999998,4.581119311"},"Riópar":{"cartodb_id":4229,"x_coordinate":167.53246753246754,"y_coordinate":116.7792083063316,"radius":71.00494233937397,"color":["#64B7DE"],"children_json_url":null,"censo_total":1214,"porcentaje_participacion":85.00823723228996,"partido_1":["PP",62.0],"partido_2":["PSOE",36.0],"partido_3":["A.E.A",0.0],"resto_partidos_percent":1,"info":"","parent":["Castilla-La_Mancha","Albacete"],"parent_url":["json/generated_data/autonomias/paro_normalizado_2003.json","json/generated_data/provincias/Castilla-La_Mancha_paro_normalizado_2003.json"],"parent_results":{"partido_1":["PSOE",44],"partido_2":["PP",17],"partido_3":["IU",5],"otros":["Otros",33]},"evolution":"2.892523077,4.072307692000001,1.9331384619999996,0.5718461539999997,0.6715076919999996,1.6692923080000002,1.522307692,0.7808923079999999,1.8744,2.937938462,1.8053230769999997,1.895509074,1.8380073799999996,1.7811193109999994"},"Bogarra":{"cartodb_id":4193,"x_coordinate":-154.54545454545456,"y_coordinate":222.0666081932631,"radius":66.05633802816902,"color":["#D94B5F"],"children_json_url":null,"censo_total":1136,"porcentaje_participacion":76.76056338028168,"partido_1":["PSOE",58.0],"partido_2":["PP",37.0],"partido_3":["A.E.A",0.0],"resto_partidos_percent":4,"info":"","parent":["Castilla-La_Mancha","Albacete"],"parent_url":["json/generated_data/autonomias/paro_normalizado_2003.json","json/generated_data/provincias/Castilla-La_Mancha_paro_normalizado_2003.json"],"parent_results":{"partido_1":["PSOE",44],"partido_2":["PP",17],"partido_3":["IU",5],"otros":["Otros",33]},"evolution":"12.892523077,14.272307692000002,13.033138461999998,10.071846154,11.371507692,10.569292308,5.822307692,5.680892308000001,3.8744,6.337938462,6.6053230769999995,6.195509074,6.83800738,5.4811193110000005"},"Higueruela":{"cartodb_id":4156,"x_coordinate":-110.3896103896104,"y_coordinate":103.88687362629918,"radius":72.23529411764706,"color":["#D94B5F"],"children_json_url":null,"censo_total":1105,"porcentaje_participacion":87.05882352941177,"partido_1":["PSOE",33.0],"partido_2":["UPH",29.0],"partido_3":["PP",26.0],"resto_partidos_percent":11,"info":"","parent":["Castilla-La_Mancha","Albacete"],"parent_url":["json/generated_data/autonomias/paro_normalizado_2003.json","json/generated_data/provincias/Castilla-La_Mancha_paro_normalizado_2003.json"],"parent_results":{"partido_1":["PSOE",44],"partido_2":["PP",17],"partido_3":["IU",5],"otros":["Otros",33]},"evolution":"-0.7074769229999998,-1.6276923079999994,-1.166861538,-2.4281538460000003,-1.5284923080000001,-1.030707692,-0.07769230800000004,0.18089230799999978,0.2744,1.2379384619999998,1.4053230770000003,1.9955090740000005,0.33800737999999964,-0.9188806889999999"},"Molinicos":{"cartodb_id":4198,"x_coordinate":-183.11688311688312,"y_coordinate":170.49726947313337,"radius":68.64422202001819,"color":["#D94B5F"],"children_json_url":null,"censo_total":1099,"porcentaje_participacion":81.07370336669699,"partido_1":["PSOE",56.0],"partido_2":["PP",24.0],"partido_3":["ALIMYA",19.0],"resto_partidos_percent":0,"info":"","parent":["Castilla-La_Mancha","Albacete"],"parent_url":["json/generated_data/autonomias/paro_normalizado_2003.json","json/generated_data/provincias/Castilla-La_Mancha_paro_normalizado_2003.json"],"parent_results":{"partido_1":["PSOE",44],"partido_2":["PP",17],"partido_3":["IU",5],"otros":["Otros",33]},"evolution":"2.2925230770000002,1.8723076920000006,1.833138462,2.7718461539999995,2.9715076919999994,3.669292308,4.822307692,3.280892308,3.9743999999999997,6.437938462,5.205323076999999,5.995509074000001,3.03800738,2.2811193109999994"},"Casas_de_Juan_Núñez":{"cartodb_id":896,"x_coordinate":-102.59740259740259,"y_coordinate":144.7126001130685,"radius":74.21686746987952,"color":["#D94B5F"],"children_json_url":null,"censo_total":1079,"porcentaje_participacion":90.36144578313254,"partido_1":["PSOE",49.0],"partido_2":["PP",48.0],"partido_3":["A.E.A",0.0],"resto_partidos_percent":1,"info":"","parent":["Castilla-La_Mancha","Albacete"],"parent_url":["json/generated_data/autonomias/paro_normalizado_2003.json","json/generated_data/provincias/Castilla-La_Mancha_paro_normalizado_2003.json"],"parent_results":{"partido_1":["PSOE",44],"partido_2":["PP",17],"partido_3":["IU",5],"otros":["Otros",33]},"evolution":"1.2925230770000002,2.5723076920000008,1.833138462,1.7718461539999995,1.071507692,2.269292308,2.9223076919999995,2.0808923079999997,0.8744000000000001,3.5379384619999996,2.4053230770000003,3.395509074,2.23800738,1.5811193110000001"},"Letur":{"cartodb_id":4196,"x_coordinate":-198.7012987012987,"y_coordinate":187.6870490465099,"radius":66.61668228678538,"color":["#D94B5F"],"children_json_url":null,"censo_total":1067,"porcentaje_participacion":77.69447047797563,"partido_1":["PSOE",68.0],"partido_2":["PP",30.0],"partido_3":["A.E.A",0.0],"resto_partidos_percent":0,"info":"","parent":["Castilla-La_Mancha","Albacete"],"parent_url":["json/generated_data/autonomias/paro_normalizado_2003.json","json/generated_data/provincias/Castilla-La_Mancha_paro_normalizado_2003.json"],"parent_results":{"partido_1":["PSOE",44],"partido_2":["PP",17],"partido_3":["IU",5],"otros":["Otros",33]},"evolution":"3.592523076999999,4.172307692,3.7331384619999994,4.171846154,3.9715076919999994,6.069292308,4.722307692,4.080892307999999,5.1744,7.237938462000001,6.005323077,6.795509074,4.73800738,5.4811193110000005"},"San_Pedro":{"cartodb_id":4232,"x_coordinate":-131.16883116883116,"y_coordinate":168.34854702646132,"radius":74.65791940018744,"color":["#D94B5F"],"children_json_url":null,"censo_total":1067,"porcentaje_participacion":91.09653233364574,"partido_1":["PSOE",55.0],"partido_2":["PP",43.0],"partido_3":["A.E.A",0.0],"resto_partidos_percent":1,"info":"","parent":["Castilla-La_Mancha","Albacete"],"parent_url":["json/generated_data/autonomias/paro_normalizado_2003.json","json/generated_data/provincias/Castilla-La_Mancha_paro_normalizado_2003.json"],"parent_results":{"partido_1":["PSOE",44],"partido_2":["PP",17],"partido_3":["IU",5],"otros":["Otros",33]},"evolution":"4.592523076999999,3.5723076920000008,2.7331384619999994,1.9718461539999996,1.7715076920000001,2.469292308,3.2223076920000002,3.1808923080000002,2.9743999999999997,3.0379384619999996,2.9053230770000003,2.195509074,3.1380073799999995,2.181119311"},"Peñas_de_San_Pedro":{"cartodb_id":4161,"x_coordinate":180.5194805194805,"y_coordinate":142.56387766639645,"radius":71.09859154929578,"color":["#64B7DE"],"children_json_url":null,"censo_total":1065,"porcentaje_participacion":85.16431924882629,"partido_1":["PP",63.0],"partido_2":["PSOE",32.0],"partido_3":["IU",2.0],"resto_partidos_percent":0,"info":"","parent":["Castilla-La_Mancha","Albacete"],"parent_url":["json/generated_data/autonomias/paro_normalizado_2003.json","json/generated_data/provincias/Castilla-La_Mancha_paro_normalizado_2003.json"],"parent_results":{"partido_1":["PSOE",44],"partido_2":["PP",17],"partido_3":["IU",5],"otros":["Otros",33]},"evolution":"2.7925230770000002,4.172307692,4.533138462,2.871846154,2.771507692,1.469292308,4.022307692,1.980892308,2.1744,3.637938462,3.4053230770000003,0.7955090740000004,1.6380073799999995,1.381119310999999"},"Villalgordo_del_Júcar":{"cartodb_id":4215,"x_coordinate":105.1948051948052,"y_coordinate":-71.6560369262181,"radius":72.89772727272728,"color":["#64B7DE"],"children_json_url":null,"censo_total":1056,"porcentaje_participacion":88.16287878787878,"partido_1":["PP",43.0],"partido_2":["PSOE",41.0],"partido_3":["IU",14.0],"resto_partidos_percent":0,"info":"","parent":["Castilla-La_Mancha","Albacete"],"parent_url":["json/generated_data/autonomias/paro_normalizado_2003.json","json/generated_data/provincias/Castilla-La_Mancha_paro_normalizado_2003.json"],"parent_results":{"partido_1":["PSOE",44],"partido_2":["PP",17],"partido_3":["IU",5],"otros":["Otros",33]},"evolution":"-0.7074769229999998,-1.0276923079999998,-0.3668615380000002,-1.128153846,-0.42849230800000004,-1.230707692,-1.877692308,-1.3191076920000002,-0.6255999999999999,-0.6620615380000001,-1.6946769230000003,-1.7044909259999996,-1.9619926200000002,-2.818880689"},"Bonete":{"cartodb_id":4188,"x_coordinate":-136.36363636363637,"y_coordinate":-95.2919838396109,"radius":74.22492401215806,"color":["#D94B5F"],"children_json_url":null,"censo_total":987,"porcentaje_participacion":90.37487335359677,"partido_1":["PSOE",55.0],"partido_2":["PP",41.0],"partido_3":["A.E.A",0.0],"resto_partidos_percent":2,"info":"","parent":["Castilla-La_Mancha","Albacete"],"parent_url":["json/generated_data/autonomias/paro_normalizado_2003.json","json/generated_data/provincias/Castilla-La_Mancha_paro_normalizado_2003.json"],"parent_results":{"partido_1":["PSOE",44],"partido_2":["PP",17],"partido_3":["IU",5],"otros":["Otros",33]},"evolution":"1.9925230769999995,-0.3276923079999996,-0.5668615380000004,-0.9281538460000003,-1.7284923080000003,-1.530707692,-0.977692308,-0.21910769200000013,-0.12559999999999993,-1.1620615380000001,-0.5946769230000002,-0.4044909259999998,0.23800738,0.7811193109999994"},"Ayna":{"cartodb_id":4192,"x_coordinate":-102.59740259740259,"y_coordinate":null,"radius":72.05338809034907,"color":["#D94B5F"],"children_json_url":null,"censo_total":974,"porcentaje_participacion":86.75564681724846,"partido_1":["PSOE",50.0],"partido_2":["PP",49.0],"partido_3":["A.E.A",0.0],"resto_partidos_percent":0,"info":"","parent":["Castilla-La_Mancha","Albacete"],"parent_url":["json/generated_data/autonomias/paro_normalizado_2003.json","json/generated_data/provincias/Castilla-La_Mancha_paro_normalizado_2003.json"],"parent_results":{"partido_1":["PSOE",44],"partido_2":["PP",17],"partido_3":["IU",5],"otros":["Otros",33]},"evolution":""},"Cenizate":{"cartodb_id":4163,"x_coordinate":-131.16883116883116,"y_coordinate":138.26643277305232,"radius":70.2405498281787,"color":["#D94B5F"],"children_json_url":null,"censo_total":873,"porcentaje_participacion":83.73424971363116,"partido_1":["PSOE",48.0],"partido_2":["PP",36.0],"partido_3":["IU",12.0],"resto_partidos_percent":2,"info":"","parent":["Castilla-La_Mancha","Albacete"],"parent_url":["json/generated_data/autonomias/paro_normalizado_2003.json","json/generated_data/provincias/Castilla-La_Mancha_paro_normalizado_2003.json"],"parent_results":{"partido_1":["PSOE",44],"partido_2":["PP",17],"partido_3":["IU",5],"otros":["Otros",33]},"evolution":"6.392523077,4.772307692,3.033138462,1.9718461539999996,2.6715076919999996,3.469292308,3.022307692,1.7808923079999999,2.1744,3.8379384620000003,3.3053230769999997,2.9955090740000005,2.03800738,2.181119311"},"Abengibre":{"cartodb_id":4168,"x_coordinate":-149.35064935064935,"y_coordinate":null,"radius":74.95327102803739,"color":["#D94B5F"],"children_json_url":null,"censo_total":856,"porcentaje_participacion":91.58878504672897,"partido_1":["PSOE",58.0],"partido_2":["PP",39.0],"partido_3":["A.E.A",0.0],"resto_partidos_percent":1,"info":"","parent":["Castilla-La_Mancha","Albacete"],"parent_url":["json/generated_data/autonomias/paro_normalizado_2003.json","json/generated_data/provincias/Castilla-La_Mancha_paro_normalizado_2003.json"],"parent_results":{"partido_1":["PSOE",44],"partido_2":["PP",17],"partido_3":["IU",5],"otros":["Otros",33]},"evolution":""},"Hoya-Gonzalo":{"cartodb_id":4157,"x_coordinate":125.97402597402598,"y_coordinate":null,"radius":77.42962056303548,"color":["#64B7DE"],"children_json_url":null,"censo_total":817,"porcentaje_participacion":95.71603427172583,"partido_1":["PP",54.0],"partido_2":["PSOE",44.0],"partido_3":["A.E.A",0.0],"resto_partidos_percent":0,"info":"","parent":["Castilla-La_Mancha","Albacete"],"parent_url":["json/generated_data/autonomias/paro_normalizado_2003.json","json/generated_data/provincias/Castilla-La_Mancha_paro_normalizado_2003.json"],"parent_results":{"partido_1":["PSOE",44],"partido_2":["PP",17],"partido_3":["IU",5],"otros":["Otros",33]},"evolution":""},"Casas_de_Ves":{"cartodb_id":3878,"x_coordinate":120.77922077922078,"y_coordinate":null,"radius":66.45885286783042,"color":["#64B7DE"],"children_json_url":null,"censo_total":802,"porcentaje_participacion":77.43142144638404,"partido_1":["PP",53.0],"partido_2":["PSOE",45.0],"partido_3":["A.E.A",0.0],"resto_partidos_percent":1,"info":"","parent":["Castilla-La_Mancha","Albacete"],"parent_url":["json/generated_data/autonomias/paro_normalizado_2003.json","json/generated_data/provincias/Castilla-La_Mancha_paro_normalizado_2003.json"],"parent_results":{"partido_1":["PSOE",44],"partido_2":["PP",17],"partido_3":["IU",5],"otros":["Otros",33]},"evolution":""},"Pétrola":{"cartodb_id":4162,"x_coordinate":102.59740259740259,"y_coordinate":null,"radius":73.44473007712082,"color":["#64B7DE"],"children_json_url":null,"censo_total":778,"porcentaje_participacion":89.0745501285347,"partido_1":["PP",50.0],"partido_2":["PSOE",49.0],"partido_3":["A.E.A",0.0],"resto_partidos_percent":0,"info":"","parent":["Castilla-La_Mancha","Albacete"],"parent_url":["json/generated_data/autonomias/paro_normalizado_2003.json","json/generated_data/provincias/Castilla-La_Mancha_paro_normalizado_2003.json"],"parent_results":{"partido_1":["PSOE",44],"partido_2":["PP",17],"partido_3":["IU",5],"otros":["Otros",33]},"evolution":""},"Albatana":{"cartodb_id":4202,"x_coordinate":-154.54545454545456,"y_coordinate":null,"radius":72.97442799461642,"color":["#D94B5F"],"children_json_url":null,"censo_total":743,"porcentaje_participacion":88.29071332436071,"partido_1":["PSOE",60.0],"partido_2":["PP",39.0],"partido_3":["A.E.A",0.0],"resto_partidos_percent":0,"info":"","parent":["Castilla-La_Mancha","Albacete"],"parent_url":["json/generated_data/autonomias/paro_normalizado_2003.json","json/generated_data/provincias/Castilla-La_Mancha_paro_normalizado_2003.json"],"parent_results":{"partido_1":["PSOE",44],"partido_2":["PP",17],"partido_3":["IU",5],"otros":["Otros",33]},"evolution":""},"Bienservida":{"cartodb_id":4219,"x_coordinate":-159.74025974025975,"y_coordinate":null,"radius":72.12976022566995,"color":["#D94B5F"],"children_json_url":null,"censo_total":709,"porcentaje_participacion":86.88293370944993,"partido_1":["PSOE",56.0],"partido_2":["PP",33.0],"partido_3":["IU",9.0],"resto_partidos_percent":0,"info":"","parent":["Castilla-La_Mancha","Albacete"],"parent_url":["json/generated_data/autonomias/paro_normalizado_2003.json","json/generated_data/provincias/Castilla-La_Mancha_paro_normalizado_2003.json"],"parent_results":{"partido_1":["PSOE",44],"partido_2":["PP",17],"partido_3":["IU",5],"otros":["Otros",33]},"evolution":""},"Férez":{"cartodb_id":4195,"x_coordinate":-151.94805194805195,"y_coordinate":null,"radius":72.58522727272728,"color":["#D94B5F"],"children_json_url":null,"censo_total":704,"porcentaje_participacion":87.64204545454545,"partido_1":["PSOE",58.0],"partido_2":["PP",38.0],"partido_3":["IU",2.0],"resto_partidos_percent":0,"info":"","parent":["Castilla-La_Mancha","Albacete"],"parent_url":["json/generated_data/autonomias/paro_normalizado_2003.json","json/generated_data/provincias/Castilla-La_Mancha_paro_normalizado_2003.json"],"parent_results":{"partido_1":["PSOE",44],"partido_2":["PP",17],"partido_3":["IU",5],"otros":["Otros",33]},"evolution":""},"Villapalacios":{"cartodb_id":4235,"x_coordinate":-112.98701298701299,"y_coordinate":null,"radius":68.11965811965811,"color":["#D94B5F"],"children_json_url":null,"censo_total":702,"porcentaje_participacion":80.1994301994302,"partido_1":["PSOE",51.0],"partido_2":["PP",46.0],"partido_3":["A.E.A",0.0],"resto_partidos_percent":1,"info":"","parent":["Castilla-La_Mancha","Albacete"],"parent_url":["json/generated_data/autonomias/paro_normalizado_2003.json","json/generated_data/provincias/Castilla-La_Mancha_paro_normalizado_2003.json"],"parent_results":{"partido_1":["PSOE",44],"partido_2":["PP",17],"partido_3":["IU",5],"otros":["Otros",33]},"evolution":""},"Alcadozo":{"cartodb_id":4153,"x_coordinate":-100.0,"y_coordinate":null,"radius":72.74052478134111,"color":["#D94B5F"],"children_json_url":null,"censo_total":686,"porcentaje_participacion":87.90087463556851,"partido_1":["PSOE",49.0],"partido_2":["PP",49.0],"partido_3":["A.E.A",0.0],"resto_partidos_percent":0,"info":"","parent":["Castilla-La_Mancha","Albacete"],"parent_url":["json/generated_data/autonomias/paro_normalizado_2003.json","json/generated_data/provincias/Castilla-La_Mancha_paro_normalizado_2003.json"],"parent_results":{"partido_1":["PSOE",44],"partido_2":["PP",17],"partido_3":["IU",5],"otros":["Otros",33]},"evolution":""},"Alborea":{"cartodb_id":4170,"x_coordinate":-188.31168831168833,"y_coordinate":null,"radius":72.13855421686748,"color":["#D94B5F"],"children_json_url":null,"censo_total":664,"porcentaje_participacion":86.8975903614458,"partido_1":["PSOE",66.0],"partido_2":["PP",32.0],"partido_3":["A.E.A",0.0],"resto_partidos_percent":0,"info":"","parent":["Castilla-La_Mancha","Albacete"],"parent_url":["json/generated_data/autonomias/paro_normalizado_2003.json","json/generated_data/provincias/Castilla-La_Mancha_paro_normalizado_2003.json"],"parent_results":{"partido_1":["PSOE",44],"partido_2":["PP",17],"partido_3":["IU",5],"otros":["Otros",33]},"evolution":""},"Pozo-Lorente":{"cartodb_id":4179,"x_coordinate":-131.16883116883116,"y_coordinate":null,"radius":69.53150242326333,"color":["#D94B5F"],"children_json_url":null,"censo_total":619,"porcentaje_participacion":82.55250403877221,"partido_1":["PSOE",55.0],"partido_2":["PP",43.0],"partido_3":["A.E.A",0.0],"resto_partidos_percent":1,"info":"","parent":["Castilla-La_Mancha","Albacete"],"parent_url":["json/generated_data/autonomias/paro_normalizado_2003.json","json/generated_data/provincias/Castilla-La_Mancha_paro_normalizado_2003.json"],"parent_results":{"partido_1":["PSOE",44],"partido_2":["PP",17],"partido_3":["IU",5],"otros":["Otros",33]},"evolution":""},"Carcelén":{"cartodb_id":895,"x_coordinate":105.1948051948052,"y_coordinate":null,"radius":70.7843137254902,"color":["#64B7DE"],"children_json_url":null,"censo_total":612,"porcentaje_participacion":84.640522875817,"partido_1":["PP",50.0],"partido_2":["PSOE",48.0],"partido_3":["A.E.A",0.0],"resto_partidos_percent":0,"info":"","parent":["Castilla-La_Mancha","Albacete"],"parent_url":["json/generated_data/autonomias/paro_normalizado_2003.json","json/generated_data/provincias/Castilla-La_Mancha_paro_normalizado_2003.json"],"parent_results":{"partido_1":["PSOE",44],"partido_2":["PP",17],"partido_3":["IU",5],"otros":["Otros",33]},"evolution":""},"Alatoz":{"cartodb_id":4169,"x_coordinate":-157.14285714285714,"y_coordinate":null,"radius":72.71794871794872,"color":["#D94B5F"],"children_json_url":null,"censo_total":585,"porcentaje_participacion":87.86324786324786,"partido_1":["PSOE",59.0],"partido_2":["PP",37.0],"partido_3":["A.E.A",0.0],"resto_partidos_percent":3,"info":"","parent":["Castilla-La_Mancha","Albacete"],"parent_url":["json/generated_data/autonomias/paro_normalizado_2003.json","json/generated_data/provincias/Castilla-La_Mancha_paro_normalizado_2003.json"],"parent_results":{"partido_1":["PSOE",44],"partido_2":["PP",17],"partido_3":["IU",5],"otros":["Otros",33]},"evolution":""},"Salobre":{"cartodb_id":4231,"x_coordinate":-240.25974025974025,"y_coordinate":null,"radius":69.55116696588868,"color":["#D8282A"],"children_json_url":null,"censo_total":557,"porcentaje_participacion":82.58527827648115,"partido_1":["PSOE",76.0],"partido_2":["PP",22.0],"partido_3":["A.E.A",0.0],"resto_partidos_percent":1,"info":"","parent":["Castilla-La_Mancha","Albacete"],"parent_url":["json/generated_data/autonomias/paro_normalizado_2003.json","json/generated_data/provincias/Castilla-La_Mancha_paro_normalizado_2003.json"],"parent_results":{"partido_1":["PSOE",44],"partido_2":["PP",17],"partido_3":["IU",5],"otros":["Otros",33]},"evolution":""},"Povedilla":{"cartodb_id":4228,"x_coordinate":133.76623376623377,"y_coordinate":null,"radius":74.07678244972578,"color":["#64B7DE"],"children_json_url":null,"censo_total":547,"porcentaje_participacion":90.12797074954297,"partido_1":["PP",56.0],"partido_2":["PSOE",43.0],"partido_3":["A.E.A",0.0],"resto_partidos_percent":0,"info":"","parent":["Castilla-La_Mancha","Albacete"],"parent_url":["json/generated_data/autonomias/paro_normalizado_2003.json","json/generated_data/provincias/Castilla-La_Mancha_paro_normalizado_2003.json"],"parent_results":{"partido_1":["PSOE",44],"partido_2":["PP",17],"partido_3":["IU",5],"otros":["Otros",33]},"evolution":""},"Jorquera":{"cartodb_id":4173,"x_coordinate":170.12987012987014,"y_coordinate":null,"radius":69.92277992277992,"color":["#64B7DE"],"children_json_url":null,"censo_total":518,"porcentaje_participacion":83.20463320463321,"partido_1":["PP",62.0],"partido_2":["PSOE",35.0],"partido_3":["IU",1.0],"resto_partidos_percent":1,"info":"","parent":["Castilla-La_Mancha","Albacete"],"parent_url":["json/generated_data/autonomias/paro_normalizado_2003.json","json/generated_data/provincias/Castilla-La_Mancha_paro_normalizado_2003.json"],"parent_results":{"partido_1":["PSOE",44],"partido_2":["PP",17],"partido_3":["IU",5],"otros":["Otros",33]},"evolution":""},"El_Ballestero":{"cartodb_id":4223,"x_coordinate":-167.53246753246754,"y_coordinate":null,"radius":73.56701030927834,"color":["#D94B5F"],"children_json_url":null,"censo_total":485,"porcentaje_participacion":89.27835051546393,"partido_1":["PSOE",54.0],"partido_2":["PP",28.0],"partido_3":["IU",16.0],"resto_partidos_percent":0,"info":"","parent":["Castilla-La_Mancha","Albacete"],"parent_url":["json/generated_data/autonomias/paro_normalizado_2003.json","json/generated_data/provincias/Castilla-La_Mancha_paro_normalizado_2003.json"],"parent_results":{"partido_1":["PSOE",44],"partido_2":["PP",17],"partido_3":["IU",5],"otros":["Otros",33]},"evolution":""},"Navas_de_Jorquera":{"cartodb_id":4178,"x_coordinate":123.37662337662337,"y_coordinate":null,"radius":69.33618843683084,"color":["#64B7DE"],"children_json_url":null,"censo_total":467,"porcentaje_participacion":82.22698072805139,"partido_1":["PP",52.0],"partido_2":["PSOE",43.0],"partido_3":["A.E.A",0.0],"resto_partidos_percent":3,"info":"","parent":["Castilla-La_Mancha","Albacete"],"parent_url":["json/generated_data/autonomias/paro_normalizado_2003.json","json/generated_data/provincias/Castilla-La_Mancha_paro_normalizado_2003.json"],"parent_results":{"partido_1":["PSOE",44],"partido_2":["PP",17],"partido_3":["IU",5],"otros":["Otros",33]},"evolution":""},"Paterna_del_Madera":{"cartodb_id":4225,"x_coordinate":-128.57142857142858,"y_coordinate":null,"radius":67.61290322580646,"color":["#D94B5F"],"children_json_url":null,"censo_total":465,"porcentaje_participacion":79.35483870967742,"partido_1":["PSOE",55.0],"partido_2":["PP",44.0],"partido_3":["A.E.A",0.0],"resto_partidos_percent":0,"info":"","parent":["Castilla-La_Mancha","Albacete"],"parent_url":["json/generated_data/autonomias/paro_normalizado_2003.json","json/generated_data/provincias/Castilla-La_Mancha_paro_normalizado_2003.json"],"parent_results":{"partido_1":["PSOE",44],"partido_2":["PP",17],"partido_3":["IU",5],"otros":["Otros",33]},"evolution":""},"Viveros":{"cartodb_id":4237,"x_coordinate":-136.36363636363637,"y_coordinate":null,"radius":71.96544276457882,"color":["#D94B5F"],"children_json_url":null,"censo_total":463,"porcentaje_participacion":86.60907127429806,"partido_1":["PSOE",56.0],"partido_2":["PP",42.0],"partido_3":["A.E.A",0.0],"resto_partidos_percent":1,"info":"","parent":["Castilla-La_Mancha","Albacete"],"parent_url":["json/generated_data/autonomias/paro_normalizado_2003.json","json/generated_data/provincias/Castilla-La_Mancha_paro_normalizado_2003.json"],"parent_results":{"partido_1":["PSOE",44],"partido_2":["PP",17],"partido_3":["IU",5],"otros":["Otros",33]},"evolution":""},"Motilleja":{"cartodb_id":4177,"x_coordinate":-196.1038961038961,"y_coordinate":null,"radius":73.92070484581498,"color":["#D94B5F"],"children_json_url":null,"censo_total":454,"porcentaje_participacion":89.86784140969164,"partido_1":["PSOE",67.0],"partido_2":["PP",30.0],"partido_3":["A.E.A",0.0],"resto_partidos_percent":1,"info":"","parent":["Castilla-La_Mancha","Albacete"],"parent_url":["json/generated_data/autonomias/paro_normalizado_2003.json","json/generated_data/provincias/Castilla-La_Mancha_paro_normalizado_2003.json"],"parent_results":{"partido_1":["PSOE",44],"partido_2":["PP",17],"partido_3":["IU",5],"otros":["Otros",33]},"evolution":""},"Vianos":{"cartodb_id":4234,"x_coordinate":105.1948051948052,"y_coordinate":null,"radius":71.46666666666667,"color":["#64B7DE"],"children_json_url":null,"censo_total":450,"porcentaje_participacion":85.77777777777777,"partido_1":["PP",50.0],"partido_2":["PSOE",48.0],"partido_3":["A.E.A",0.0],"resto_partidos_percent":0,"info":"","parent":["Castilla-La_Mancha","Albacete"],"parent_url":["json/generated_data/autonomias/paro_normalizado_2003.json","json/generated_data/provincias/Castilla-La_Mancha_paro_normalizado_2003.json"],"parent_results":{"partido_1":["PSOE",44],"partido_2":["PP",17],"partido_3":["IU",5],"otros":["Otros",33]},"evolution":""},"Corral-Rubio":{"cartodb_id":4155,"x_coordinate":190.9090909090909,"y_coordinate":null,"radius":73.16628701594533,"color":["#64B7DE"],"children_json_url":null,"censo_total":439,"porcentaje_participacion":88.61047835990888,"partido_1":["PP",66.0],"partido_2":["PSOE",31.0],"partido_3":["A.E.A",0.0],"resto_partidos_percent":2,"info":"","parent":["Castilla-La_Mancha","Albacete"],"parent_url":["json/generated_data/autonomias/paro_normalizado_2003.json","json/generated_data/provincias/Castilla-La_Mancha_paro_normalizado_2003.json"],"parent_results":{"partido_1":["PSOE",44],"partido_2":["PP",17],"partido_3":["IU",5],"otros":["Otros",33]},"evolution":""},"Villaverde_de_Guadalimar":{"cartodb_id":4236,"x_coordinate":-125.97402597402598,"y_coordinate":null,"radius":64.67780429594272,"color":["#D94B5F"],"children_json_url":null,"censo_total":419,"porcentaje_participacion":74.46300715990454,"partido_1":["PSOE",54.0],"partido_2":["PP",44.0],"partido_3":["A.E.A",0.0],"resto_partidos_percent":0,"info":"","parent":["Castilla-La_Mancha","Albacete"],"parent_url":["json/generated_data/autonomias/paro_normalizado_2003.json","json/generated_data/provincias/Castilla-La_Mancha_paro_normalizado_2003.json"],"parent_results":{"partido_1":["PSOE",44],"partido_2":["PP",17],"partido_3":["IU",5],"otros":["Otros",33]},"evolution":""},"Casas_de_Lázaro":{"cartodb_id":4220,"x_coordinate":175.32467532467533,"y_coordinate":null,"radius":74.8905109489051,"color":["#64B7DE"],"children_json_url":null,"censo_total":411,"porcentaje_participacion":91.48418491484185,"partido_1":["PP",64.0],"partido_2":["PSOE",35.0],"partido_3":["A.E.A",0.0],"resto_partidos_percent":0,"info":"","parent":["Castilla-La_Mancha","Albacete"],"parent_url":["json/generated_data/autonomias/paro_normalizado_2003.json","json/generated_data/provincias/Castilla-La_Mancha_paro_normalizado_2003.json"],"parent_results":{"partido_1":["PSOE",44],"partido_2":["PP",17],"partido_3":["IU",5],"otros":["Otros",33]},"evolution":""},"Peñascosa":{"cartodb_id":4227,"x_coordinate":-110.3896103896104,"y_coordinate":null,"radius":71.31578947368422,"color":["#D94B5F"],"children_json_url":null,"censo_total":380,"porcentaje_participacion":85.52631578947368,"partido_1":["PSOE",51.0],"partido_2":["PP",47.0],"partido_3":["A.E.A",0.0],"resto_partidos_percent":1,"info":"","parent":["Castilla-La_Mancha","Albacete"],"parent_url":["json/generated_data/autonomias/paro_normalizado_2003.json","json/generated_data/provincias/Castilla-La_Mancha_paro_normalizado_2003.json"],"parent_results":{"partido_1":["PSOE",44],"partido_2":["PP",17],"partido_3":["IU",5],"otros":["Otros",33]},"evolution":""},"Robledo":{"cartodb_id":4230,"x_coordinate":-209.0909090909091,"y_coordinate":null,"radius":70.56179775280899,"color":["#D8282A"],"children_json_url":null,"censo_total":356,"porcentaje_participacion":84.26966292134831,"partido_1":["PSOE",70.0],"partido_2":["PP",28.0],"partido_3":["A.E.A",0.0],"resto_partidos_percent":1,"info":"","parent":["Castilla-La_Mancha","Albacete"],"parent_url":["json/generated_data/autonomias/paro_normalizado_2003.json","json/generated_data/provincias/Castilla-La_Mancha_paro_normalizado_2003.json"],"parent_results":{"partido_1":["PSOE",44],"partido_2":["PP",17],"partido_3":["IU",5],"otros":["Otros",33]},"evolution":""},"Fuensanta":{"cartodb_id":4182,"x_coordinate":-211.68831168831167,"y_coordinate":null,"radius":71.91616766467067,"color":["#D8282A"],"children_json_url":null,"censo_total":334,"porcentaje_participacion":86.52694610778443,"partido_1":["PSOE",63.0],"partido_2":["PP",20.0],"partido_3":["IU",16.0],"resto_partidos_percent":0,"info":"","parent":["Castilla-La_Mancha","Albacete"],"parent_url":["json/generated_data/autonomias/paro_normalizado_2003.json","json/generated_data/provincias/Castilla-La_Mancha_paro_normalizado_2003.json"],"parent_results":{"partido_1":["PSOE",44],"partido_2":["PP",17],"partido_3":["IU",5],"otros":["Otros",33]},"evolution":""},"La_Herrera":{"cartodb_id":4159,"x_coordinate":146.75324675324674,"y_coordinate":null,"radius":73.25,"color":["#64B7DE"],"children_json_url":null,"censo_total":320,"porcentaje_participacion":88.75,"partido_1":["PP",57.0],"partido_2":["PSOE",39.0],"partido_3":["A.E.A",0.0],"resto_partidos_percent":2,"info":"","parent":["Castilla-La_Mancha","Albacete"],"parent_url":["json/generated_data/autonomias/paro_normalizado_2003.json","json/generated_data/provincias/Castilla-La_Mancha_paro_normalizado_2003.json"],"parent_results":{"partido_1":["PSOE",44],"partido_2":["PP",17],"partido_3":["IU",5],"otros":["Otros",33]},"evolution":""},"La_Recueja":{"cartodb_id":4174,"x_coordinate":-203.8961038961039,"y_coordinate":null,"radius":70.48275862068965,"color":["#D8282A"],"children_json_url":null,"censo_total":290,"porcentaje_participacion":84.13793103448276,"partido_1":["PSOE",69.0],"partido_2":["PP",29.0],"partido_3":["A.E.A",0.0],"resto_partidos_percent":1,"info":"","parent":["Castilla-La_Mancha","Albacete"],"parent_url":["json/generated_data/autonomias/paro_normalizado_2003.json","json/generated_data/provincias/Castilla-La_Mancha_paro_normalizado_2003.json"],"parent_results":{"partido_1":["PSOE",44],"partido_2":["PP",17],"partido_3":["IU",5],"otros":["Otros",33]},"evolution":""},"Villavaliente":{"cartodb_id":4185,"x_coordinate":-151.94805194805195,"y_coordinate":null,"radius":74.40298507462687,"color":["#D94B5F"],"children_json_url":null,"censo_total":268,"porcentaje_participacion":90.67164179104478,"partido_1":["PSOE",58.0],"partido_2":["PP",38.0],"partido_3":["A.E.A",0.0],"resto_partidos_percent":2,"info":"","parent":["Castilla-La_Mancha","Albacete"],"parent_url":["json/generated_data/autonomias/paro_normalizado_2003.json","json/generated_data/provincias/Castilla-La_Mancha_paro_normalizado_2003.json"],"parent_results":{"partido_1":["PSOE",44],"partido_2":["PP",17],"partido_3":["IU",5],"otros":["Otros",33]},"evolution":""},"Balsa_de_Ves":{"cartodb_id":894,"x_coordinate":185.71428571428572,"y_coordinate":null,"radius":70.0,"color":["#64B7DE"],"children_json_url":null,"censo_total":240,"porcentaje_participacion":83.33333333333334,"partido_1":["PP",64.0],"partido_2":["PSOE",31.0],"partido_3":["A.E.A",0.0],"resto_partidos_percent":3,"info":"","parent":["Castilla-La_Mancha","Albacete"],"parent_url":["json/generated_data/autonomias/paro_normalizado_2003.json","json/generated_data/provincias/Castilla-La_Mancha_paro_normalizado_2003.json"],"parent_results":{"partido_1":["PSOE",44],"partido_2":["PP",17],"partido_3":["IU",5],"otros":["Otros",33]},"evolution":""},"Villatoya":{"cartodb_id":4184,"x_coordinate":-154.54545454545456,"y_coordinate":null,"radius":69.2485549132948,"color":["#D94B5F"],"children_json_url":null,"censo_total":173,"porcentaje_participacion":82.08092485549133,"partido_1":["PSOE",58.0],"partido_2":["PP",37.0],"partido_3":["IU",2.0],"resto_partidos_percent":1,"info":"","parent":["Castilla-La_Mancha","Albacete"],"parent_url":["json/generated_data/autonomias/paro_normalizado_2003.json","json/generated_data/provincias/Castilla-La_Mancha_paro_normalizado_2003.json"],"parent_results":{"partido_1":["PSOE",44],"partido_2":["PP",17],"partido_3":["IU",5],"otros":["Otros",33]},"evolution":""},"Cotillas":{"cartodb_id":4222,"x_coordinate":-227.27272727272725,"y_coordinate":null,"radius":68.65853658536585,"color":["#D8282A"],"children_json_url":null,"censo_total":164,"porcentaje_participacion":81.09756097560977,"partido_1":["PSOE",72.0],"partido_2":["PP",23.0],"partido_3":["A.E.A",0.0],"resto_partidos_percent":4,"info":"","parent":["Castilla-La_Mancha","Albacete"],"parent_url":["json/generated_data/autonomias/paro_normalizado_2003.json","json/generated_data/provincias/Castilla-La_Mancha_paro_normalizado_2003.json"],"parent_results":{"partido_1":["PSOE",44],"partido_2":["PP",17],"partido_3":["IU",5],"otros":["Otros",33]},"evolution":""},"Montalvos":{"cartodb_id":4160,"x_coordinate":-164.93506493506493,"y_coordinate":null,"radius":70.48275862068965,"color":["#D94B5F"],"children_json_url":null,"censo_total":145,"porcentaje_participacion":84.13793103448276,"partido_1":["PSOE",60.0],"partido_2":["PP",35.0],"partido_3":["A.E.A",0.0],"resto_partidos_percent":4,"info":"","parent":["Castilla-La_Mancha","Albacete"],"parent_url":["json/generated_data/autonomias/paro_normalizado_2003.json","json/generated_data/provincias/Castilla-La_Mancha_paro_normalizado_2003.json"],"parent_results":{"partido_1":["PSOE",44],"partido_2":["PP",17],"partido_3":["IU",5],"otros":["Otros",33]},"evolution":""},"Masegoso":{"cartodb_id":4224,"x_coordinate":300.0,"y_coordinate":null,"radius":76.44444444444444,"color":["#5AB0E9"],"children_json_url":null,"censo_total":135,"porcentaje_participacion":94.07407407407408,"partido_1":["PP",87.0],"partido_2":["AIDM",10.0],"partido_3":["PSOE",2.0],"resto_partidos_percent":0,"info":"","parent":["Castilla-La_Mancha","Albacete"],"parent_url":["json/generated_data/autonomias/paro_normalizado_2003.json","json/generated_data/provincias/Castilla-La_Mancha_paro_normalizado_2003.json"],"parent_results":{"partido_1":["PSOE",44],"partido_2":["PP",17],"partido_3":["IU",5],"otros":["Otros",33]},"evolution":""},"Pozuelo":{"cartodb_id":4167,"x_coordinate":-128.57142857142858,"y_coordinate":null,"radius":62.05607476635514,"color":["#D94B5F"],"children_json_url":null,"censo_total":107,"porcentaje_participacion":70.09345794392523,"partido_1":["PSOE",50.0],"partido_2":["PP",39.0],"partido_3":["A.E.A",0.0],"resto_partidos_percent":10,"info":"","parent":["Castilla-La_Mancha","Albacete"],"parent_url":["json/generated_data/autonomias/paro_normalizado_2003.json","json/generated_data/provincias/Castilla-La_Mancha_paro_normalizado_2003.json"],"parent_results":{"partido_1":["PSOE",44],"partido_2":["PP",17],"partido_3":["IU",5],"otros":["Otros",33]},"evolution":""},"Golosalvo":{"cartodb_id":4165,"x_coordinate":183.11688311688312,"y_coordinate":null,"radius":67.88461538461539,"color":["#64B7DE"],"children_json_url":null,"censo_total":104,"porcentaje_participacion":79.8076923076923,"partido_1":["PP",62.0],"partido_2":["PSOE",30.0],"partido_3":["A.E.A",0.0],"resto_partidos_percent":7,"info":"","parent":["Castilla-La_Mancha","Albacete"],"parent_url":["json/generated_data/autonomias/paro_normalizado_2003.json","json/generated_data/provincias/Castilla-La_Mancha_paro_normalizado_2003.json"],"parent_results":{"partido_1":["PSOE",44],"partido_2":["PP",17],"partido_3":["IU",5],"otros":["Otros",33]},"evolution":""},"Villa_de_Ves":{"cartodb_id":4181,"x_coordinate":255.84415584415584,"y_coordinate":null,"radius":70.95890410958904,"color":["#5AB0E9"],"children_json_url":null,"censo_total":73,"porcentaje_participacion":84.93150684931507,"partido_1":["PP",78.0],"partido_2":["PSOE",18.0],"partido_3":["IU",1.0],"resto_partidos_percent":1,"info":"","parent":["Castilla-La_Mancha","Albacete"],"parent_url":["json/generated_data/autonomias/paro_normalizado_2003.json","json/generated_data/provincias/Castilla-La_Mancha_paro_normalizado_2003.json"],"parent_results":{"partido_1":["PSOE",44],"partido_2":["PP",17],"partido_3":["IU",5],"otros":["Otros",33]},"evolution":""}}