{"Badajoz":{"cartodb_id":39,"x_coordinate":-202.12765957446808,"y_coordinate":"0.278676714","radius":65.4166952937135,"color":"#D8282A","children_json_url":"json/generated_data/municipalities/Badajoz_saldo_vegetativo_normalizado_1987.json","censo_total":436650,"porcentaje_participacion":75.69449215618917,"partido_1":["PSOE","#D94B5F",38.0],"partido_2":["AP","#AAAAAA",14.0],"partido_3":["CDS","#AAAAAA",7.0]},"Cáceres":{"cartodb_id":40,"x_coordinate":-151.06382978723406,"y_coordinate":"-0.955570286","radius":77.09882355948886,"color":"#D94B5F","children_json_url":"json/generated_data/municipalities/Cáceres_saldo_vegetativo_normalizado_1987.json","censo_total":234691,"porcentaje_participacion":95.16470593248143,"partido_1":["PSOE","#D94B5F",31.0],"partido_2":["AP","#AAAAAA",19.0],"partido_3":["CDS","#AAAAAA",7.0]}}