{"Vizcaya":{"cartodb_id":17,"x_coordinate":0,"y_coordinate":115.5172413831748,"radius":74.99664787048826,"color":"#AAA","children_json_url":"json/generated_data/municipalities/Vizcaya_paro_normalizado_1999.json","censo_total":577245,"porcentaje_participacion":91.66107978414712,"partido_1":["EAJ-PNV/EA","#AAAAAA",33.0],"partido_2":["PSOE","#E08394",15.0],"partido_3":["PP","#90D7F4",8.0]},"Álava":{"cartodb_id":48,"x_coordinate":206.97674418604652,"y_coordinate":-81.89655172896849,"radius":61.14773633505357,"color":"#5AB0E9","children_json_url":"json/generated_data/municipalities/Álava_paro_normalizado_1999.json","censo_total":218186,"porcentaje_participacion":68.57956055842263,"partido_1":["PP","#90D7F4",26.0],"partido_2":["EAJ-PNV","#AAAAAA",3.0],"partido_3":["EAJ-PNV/EA","#AAAAAA",2.0]},"Guipúzcoa":{"cartodb_id":49,"x_coordinate":-104.65116279069767,"y_coordinate":-76.29310345326743,"radius":64.5482247208347,"color":"#D94B5F","children_json_url":"json/generated_data/municipalities/Guipúzcoa_paro_normalizado_1999.json","censo_total":311106,"porcentaje_participacion":74.24704120139116,"partido_1":["PSOE","#E08394",15.0],"partido_2":["EAJ-PNV/EA","#AAAAAA",14.0],"partido_3":["EH","#AAAAAA",12.0]}}